{
    "$schema": "https://schema.management.azure.com/schemas/2019-04-01/deploymentTemplate.json#",
    "contentVersion": "1.0.0.0",
    "parameters": {
        "location": {
            "type": "string"
        },
        "vmName": {
            "type": "string"
        },
        "SQLDataDiskSize": {
            "type": "int"
        },
        "SQLLogDiskSize": {
            "type": "int"
        },
        "SQLDataDiskCount": {
            "type": "int"
        },
        "SQLLogDiskCount": {
            "type": "int"
        },
        "SQLTempDBDiskSize": {
            "type": "int"
        },
        "zones": {
            "type": "int"
        }
    },
    "functions": [],
    "variables": {},
    "resources": [
        {
            "type": "Microsoft.Compute/virtualMachines",
            "apiVersion": "2020-06-01",
            "name": "[parameters('vmName')]",
            "location": "[parameters('location')]",
            "dependsOn": [],
            "properties": {
                "storageProfile": {
                    "copy": [
                        {
                            "name": "dataDisks",
                            "count": "[add(parameters('SQLDataDiskCount'), parameters('sqlLogDisksCount'))]",
                            "input": {
                                "lun": "[copyIndex('dataDisks')]",
                                "createOption": "[variables('dataDisks').createOption]",
                                "caching": "[if(greaterOrEquals(copyIndex('dataDisks'), parameters('sqlDataDisksCount')) ,'None', variables('dataDisks').caching )]",
                                "writeAcceleratorEnabled": "[variables('dataDisks').writeAcceleratorEnabled]",
                                "diskSizeGB": "[variables('dataDisks').diskSizeGB]",
                                "managedDisk": {
                                    "storageAccountType": "[variables('dataDisks').storageAccountType]"
                                }
                            }
                        }
                    ]
                }
            }
        }
    ],
    "outputs": {}
}